cgmodsel/__init__.py
cgmodsel/admm.py
cgmodsel/base_admm.py
cgmodsel/base_huber.py
cgmodsel/base_solver.py
cgmodsel/dataops.py
cgmodsel/huber_clz.py
cgmodsel/map.py
cgmodsel/prox.py
cgmodsel/utils.py
cgmodsel/models/__init__.py
cgmodsel/models/base.py
cgmodsel/models/model_clz.py
cgmodsel/models/model_pw.py
cgmodsel/models/model_pwsl.py
tests/__init__.py
tests/test_map.py
tests/test_pws.py
tests/test_pwsl.py
cgmodsel-1.0.dist-info/METADATA
cgmodsel-1.0.dist-info/WHEEL
cgmodsel-1.0.dist-info/top_level.txt
cgmodsel-1.0.dist-info/RECORD
