Metadata-Version: 2.1
Name: cgmodsel
Version: 1.0
Summary: Algorithms for model selection of conditional Gaussian distributions
Home-page: https://github.com/franknu/cgmodsel.git
Author: Frank Nussbaum
Author-email: frank.nussbaum@uni-jena.de
License: Public
Platform: UNKNOWN
Requires-Dist: numpy
Requires-Dist: pandas
Requires-Dist: scipy
Requires-Dist: matplotlib
